README.rst
setup.py
support_developer/__init__.py
support_developer/__version__.py
support_developer/luca.py
support_developer/support_message.py
support_developer/utils.py
support_developer.egg-info/PKG-INFO
support_developer.egg-info/SOURCES.txt
support_developer.egg-info/dependency_links.txt
support_developer.egg-info/requires.txt
support_developer.egg-info/top_level.txt