Metadata-Version: 2.1
Name: support-developer
Version: 1.0.5
Summary: Package designed to centralize messages to support developers development work.
Home-page: https://github.com/LucaCappelletti94/support_developer
Author: Luca Cappelletti
Author-email: cappelletti.luca94@gmail.com
License: MIT
Platform: UNKNOWN
Classifier: Development Status :: 3 - Alpha
Classifier: License :: OSI Approved :: MIT License
Classifier: Programming Language :: Python :: 3
Provides-Extra: test
